python_webchannel/__init__.py
python_webchannel/channel.py
python_webchannel/errors.py
python_webchannel/events.py
python_webchannel/httpcors.py
python_webchannel/options.py
python_webchannel/transport.py
python_webchannel/wire.py
python_webchannel/xhr.py
python_webchannel-0.1.0.dist-info/METADATA
python_webchannel-0.1.0.dist-info/WHEEL
python_webchannel-0.1.0.dist-info/top_level.txt
python_webchannel-0.1.0.dist-info/RECORD
