Metadata-Version: 2.4
Name: python-webchannel
Version: 0.1.0
Summary: Python implementation of the Firebase WebChannel protocol
Author-email: Hurozo <admin@hurozo.com>
License: Apache-2.0
Project-URL: Homepage, https://hurozo.com
Project-URL: Repository, https://github.com/hurozo/python-webchannel
Requires-Python: >=3.10
Requires-Dist: httpx>=0.27
Requires-Dist: anyio>=3.7
